sball/__init__.py
sball/__main__.py
sball/sball.py
sball-1.0.5.dist-info/LICENSE
sball-1.0.5.dist-info/METADATA
sball-1.0.5.dist-info/WHEEL
sball-1.0.5.dist-info/entry_points.txt
sball-1.0.5.dist-info/top_level.txt
sball-1.0.5.dist-info/RECORD
