Metadata-Version: 2.1
Name: sball
Version: 1.0.5
Summary: Submit scripts in job arrays using Yale's dSQ.
Author-email: Michael Wilson <michael.a.wilson@yale.edu>
Project-URL: Homepage, https://github.com/mawilson1234/sball
Keywords: slurm,job array,sbatch,dSQ,dsq
Classifier: Development Status :: 4 - Beta
Classifier: Programming Language :: Python
Classifier: Programming Language :: Python :: 3
Requires-Python: >=3
License-File: LICENSE
